{
    "name": "Global Information",
    "numberOfRequests": {
        "total": 290,
        "ok": 290,
        "ko": 0
    },
    "minResponseTime": {
        "total": 3,
        "ok": 3,
        "ko": 0
    },
    "maxResponseTime": {
        "total": 295,
        "ok": 295,
        "ko": 0
    },
    "meanResponseTime": {
        "total": 22,
        "ok": 22,
        "ko": 0
    },
    "standardDeviation": {
        "total": 30,
        "ok": 30,
        "ko": 0
    },
    "percentiles1": {
        "total": 12,
        "ok": 12,
        "ko": 0
    },
    "percentiles2": {
        "total": 26,
        "ok": 26,
        "ko": 0
    },
    "percentiles3": {
        "total": 62,
        "ok": 62,
        "ko": 0
    },
    "percentiles4": {
        "total": 170,
        "ok": 170,
        "ko": 0
    },
    "group1": {
    "name": "t < 800 ms",
    "count": 290,
    "percentage": 100
},
    "group2": {
    "name": "800 ms < t < 1200 ms",
    "count": 0,
    "percentage": 0
},
    "group3": {
    "name": "t > 1200 ms",
    "count": 0,
    "percentage": 0
},
    "group4": {
    "name": "failed",
    "count": 0,
    "percentage": 0
},
    "meanNumberOfRequestsPerSecond": {
        "total": 3.580246913580247,
        "ok": 3.580246913580247,
        "ko": 0
    }
}